/*
  Copyright (C) 2002, 2004, 2005, 2006 Jeroen Frijters

  This software is provided 'as-is', without any express or implied
  warranty.  In no event will the authors be held liable for any damages
  arising from the use of this software.

  Permission is granted to anyone to use this software for any purpose,
  including commercial applications, and to alter it and redistribute it
  freely, subject to the following restrictions:

  1. The origin of this software must not be misrepresented; you must not
     claim that you wrote the original software. If you use this software
     in a product, an acknowledgment in the product documentation would be
     appreciated but is not required.
  2. Altered source versions must be plainly marked as such, and must not be
     misrepresented as being the original software.
  3. This notice may not be removed or altered from any source distribution.

  Jeroen Frijters
  jeroen@frijters.net
  
*/

namespace IKVM.CoreLib.Linking
{

    internal enum NormalizedOpCode : byte
	{

		Nop = 0,
		__aconst_null = 1,
		Lconst0 = 9,
		Lconst1 = 10,
		Fconst0 = 11,
		Fconst1 = 12,
		Fconst2 = 13,
		Dconst0 = 14,
		Dconst1 = 15,
		Ldc = 18,
		Iload = 21,
		__lload = 22,
		__fload = 23,
		__dload = 24,
		__aload = 25,
		__iaload = 46,
		__laload = 47,
		__faload = 48,
		__daload = 49,
		__aaload = 50,
		__baload = 51,
		__caload = 52,
		__saload = 53,
		__istore = 54,
		__lstore = 55,
		__fstore = 56,
		__dstore = 57,
		__astore = 58,
		__iastore = 79,
		__lastore = 80,
		__fastore = 81,
		__dastore = 82,
		__aastore = 83,
		__bastore = 84,
		__castore = 85,
		__sastore = 86,
		Pop = 87,
		__pop2 = 88,
		Dup = 89,
		__dup_x1 = 90,
		__dup_x2 = 91,
		Dup2 = 92,
		__dup2_x1 = 93,
		__dup2_x2 = 94,
		__swap = 95,
		__iadd = 96,
		Ladd = 97,
		__fadd = 98,
		__dadd = 99,
		__isub = 100,
		__lsub = 101,
		__fsub = 102,
		__dsub = 103,
		__imul = 104,
		__lmul = 105,
		__fmul = 106,
		__dmul = 107,
		__idiv = 108,
		__ldiv = 109,
		__fdiv = 110,
		__ddiv = 111,
		__irem = 112,
		__lrem = 113,
		__frem = 114,
		__drem = 115,
		__ineg = 116,
		__lneg = 117,
		__fneg = 118,
		__dneg = 119,
		__ishl = 120,
		__lshl = 121,
		__ishr = 122,
		__lshr = 123,
		__iushr = 124,
		__lushr = 125,
		__iand = 126,
		__land = 127,
		Ior = 128,
		__lor = 129,
		__ixor = 130,
		__lxor = 131,
		__iinc = 132,
		__i2l = 133,
		__i2f = 134,
		__i2d = 135,
		__l2i = 136,
		__l2f = 137,
		__l2d = 138,
		F2i = 139,
		F2l = 140,
		F2d = 141,
		D2i = 142,
		D2l = 143,
		__d2f = 144,
		__i2b = 145,
		__i2c = 146,
		__i2s = 147,
		__lcmp = 148,
		__fcmpl = 149,
		__fcmpg = 150,
		__dcmpl = 151,
		__dcmpg = 152,
		Ifeq = 153,
		Ifne = 154,
		Iflt = 155,
		Ifge = 156,
		Ifgt = 157,
		Ifle = 158,
		__if_icmpeq = 159,
		__if_icmpne = 160,
		__if_icmplt = 161,
		__if_icmpge = 162,
		__if_icmpgt = 163,
		Ificmple = 164,
		Ifacmpeq = 165,
		Ifacmpne = 166,
		Goto = 167,
		Jsr = 168,
		Ret = 169,
		TableSwitch = 170,
		LookupSwitch = 171,
		Ireturn = 172,
		Lreturn = 173,
		Freturn = 174,
		Dreturn = 175,
		Areturn = 176,
		Return = 177,
		Getstatic = 178,
		__putstatic = 179,
		__getfield = 180,
		__putfield = 181,
		__invokevirtual = 182,
		__invokespecial = 183,
		__invokestatic = 184,
		__invokeinterface = 185,
		__invokedynamic = 186,
		New = 187,
		__newarray = 188,
		__anewarray = 189,
		Arraylength = 190,
		Athrow = 191,
		Checkcast = 192,
		Instanceof = 193,
		Monitorenter = 194,
		Monitorexit = 195,
		Multianewarray = 197,
		Ifnull = 198,
		Ifnonnull = 199,

		// This is where the pseudo-bytecodes start
		__privileged_invokestatic = 235, // the privileged bytecodes are used for accessing host class members
		__privileged_invokevirtual = 237,
		__privileged_invokespecial = 238,
		__ldc_nothrow = 239,
		__methodhandle_invoke = 240,
		__methodhandle_link = 241,
		__goto_finally = 242,
		__intrinsic_gettype = 243,
		__athrow_no_unmap = 244,
		__dynamic_getstatic = 245,
		__dynamic_putstatic = 246,
		__dynamic_getfield = 247,
		__dynamic_putfield = 248,
		__dynamic_invokeinterface = 249,
		__dynamic_invokestatic = 250,
		__dynamic_invokevirtual = 251,
		__dynamic_invokespecial = 252,
		__clone_array = 253,
		__static_error = 254, // not a real instruction, this signals an instruction that is compiled as an exception
		__iconst = 255,

	}

}